dflowphonon/ABACUS_OPs.py
dflowphonon/ABACUS_flow.py
dflowphonon/DP_OPs.py
dflowphonon/DP_flow.py
dflowphonon/VASP_OPs.py
dflowphonon/VASP_flow.py
dflowphonon/__init__.py
dflowphonon/test.py
dphonon-0.0.1.data/scripts/dflowphonon
dphonon-0.0.1.dist-info/LICENSE
dphonon-0.0.1.dist-info/METADATA
dphonon-0.0.1.dist-info/WHEEL
dphonon-0.0.1.dist-info/top_level.txt
dphonon-0.0.1.dist-info/RECORD
